redshift_query/__init__.py
redshift_query/cli.py
redshift_query/redshift_query.py
redshift_query-0.1.4.dist-info/LICENSE
redshift_query-0.1.4.dist-info/METADATA
redshift_query-0.1.4.dist-info/WHEEL
redshift_query-0.1.4.dist-info/entry_points.txt
redshift_query-0.1.4.dist-info/top_level.txt
redshift_query-0.1.4.dist-info/RECORD
