Metadata-Version: 2.1
Name: redshift-query
Version: 0.1.4
Summary: A simple library that runs queries on redshift!
Home-page: https://github.com/helecloud/redshift-query
Author: Farid Nouri Neshat
Author-email: faridn@helecloud.com
License: MIT license
Keywords: redshift query sql serverless lambda glue aws
Platform: UNKNOWN
Classifier: Development Status :: 2 - Pre-Alpha
Classifier: Intended Audience :: Developers
Classifier: License :: OSI Approved :: MIT License
Classifier: Natural Language :: English
Classifier: Programming Language :: Python :: 3
Classifier: Programming Language :: Python :: 3.6
Classifier: Programming Language :: Python :: 3.7
Classifier: Programming Language :: Python :: 3.8
Requires-Python: >=3.6
Requires-Dist: pygresql (~=5.2)
Requires-Dist: boto3 (~=1.16.37)
